[
  {
    "page": "home",
    "url": "https://dylanbochman.com",
    "performance": 85,
    "accessibility": 100,
    "seo": 100,
    "bestPractices": 100,
    "lcp": "3.3 s",
    "fcp": "3.0 s",
    "cls": "0",
    "tbt": "140 ms",
    "runs": 3,
    "performanceRange": [
      85,
      99
    ],
    "tbtRangeMs": [
      98,
      156
    ],
    "collectedAt": "2026-07-13T09:03:36.122Z"
  },
  {
    "page": "blog",
    "url": "https://dylanbochman.com/blog",
    "performance": 76,
    "accessibility": 96,
    "seo": 100,
    "bestPractices": 100,
    "lcp": "5.0 s",
    "fcp": "2.8 s",
    "cls": "0",
    "tbt": "120 ms",
    "runs": 3,
    "performanceRange": [
      73,
      76
    ],
    "tbtRangeMs": [
      119,
      133
    ],
    "collectedAt": "2026-07-13T09:03:36.122Z"
  },
  {
    "page": "blog-post-404",
    "url": "https://dylanbochman.com/blog/2026-01-08-fixing-404-errors-on-github-pages-spas",
    "performance": 69,
    "accessibility": 100,
    "seo": 100,
    "bestPractices": 100,
    "lcp": "10.6 s",
    "fcp": "3.0 s",
    "cls": "0",
    "tbt": "120 ms",
    "runs": 3,
    "performanceRange": [
      68,
      69
    ],
    "tbtRangeMs": [
      123,
      136
    ],
    "collectedAt": "2026-07-13T09:03:36.122Z"
  },
  {
    "page": "projects",
    "url": "https://dylanbochman.com/projects",
    "performance": 88,
    "accessibility": 98,
    "seo": 100,
    "bestPractices": 100,
    "lcp": "3.2 s",
    "fcp": "2.8 s",
    "cls": "0",
    "tbt": "110 ms",
    "runs": 3,
    "performanceRange": [
      77,
      88
    ],
    "tbtRangeMs": [
      99,
      115
    ],
    "collectedAt": "2026-07-13T09:03:36.122Z"
  },
  {
    "page": "project-slo",
    "url": "https://dylanbochman.com/projects/slo-tool",
    "performance": 69,
    "accessibility": 92,
    "seo": 100,
    "bestPractices": 100,
    "lcp": "9.7 s",
    "fcp": "2.9 s",
    "cls": "0",
    "tbt": "110 ms",
    "runs": 3,
    "performanceRange": [
      68,
      69
    ],
    "tbtRangeMs": [
      110,
      151
    ],
    "collectedAt": "2026-07-13T09:03:36.122Z"
  },
  {
    "page": "project-statuspage",
    "url": "https://dylanbochman.com/projects/statuspage-update",
    "performance": 78,
    "accessibility": 96,
    "seo": 100,
    "bestPractices": 100,
    "lcp": "4.4 s",
    "fcp": "2.9 s",
    "cls": "0",
    "tbt": "130 ms",
    "runs": 3,
    "performanceRange": [
      75,
      80
    ],
    "tbtRangeMs": [
      101,
      125
    ],
    "collectedAt": "2026-07-13T09:03:36.122Z"
  },
  {
    "page": "project-oncall",
    "url": "https://dylanbochman.com/projects/oncall-coverage",
    "performance": 78,
    "accessibility": 96,
    "seo": 100,
    "bestPractices": 100,
    "lcp": "4.6 s",
    "fcp": "2.9 s",
    "cls": "0",
    "tbt": "120 ms",
    "runs": 3,
    "performanceRange": [
      74,
      83
    ],
    "tbtRangeMs": [
      99,
      115
    ],
    "collectedAt": "2026-07-13T09:03:36.122Z"
  },
  {
    "page": "runbook",
    "url": "https://dylanbochman.com/runbook",
    "performance": 79,
    "accessibility": 100,
    "seo": 100,
    "bestPractices": 100,
    "lcp": "4.3 s",
    "fcp": "3.0 s",
    "cls": "0",
    "tbt": "100 ms",
    "runs": 3,
    "performanceRange": [
      78,
      82
    ],
    "tbtRangeMs": [
      94,
      114
    ],
    "collectedAt": "2026-07-13T09:03:36.122Z"
  }
]