{
  "generated": "2026-03-13T06:16:37.143Z",
  "searchConsole": {
    "lastCheck": "2026-01-12T11:03:07.421Z",
    "clicks": 0,
    "impressions": 1,
    "averageCTR": 0,
    "averagePosition": 1
  },
  "analytics": {
    "lastCheck": "2026-03-13T06:16:37.143Z",
    "sessions_7d": 354,
    "users_7d": 332,
    "pageviews_7d": 332,
    "avgSessionDuration": 15,
    "bounceRate": 0.76,
    "topPages": [
      {
        "page": "/blog/",
        "pageViews": 76
      },
      {
        "page": "/",
        "pageViews": 67
      },
      {
        "page": "/blog/2026-01-25-dotfiles-for-ai-assisted-development/",
        "pageViews": 28
      },
      {
        "page": "/blog",
        "pageViews": 20
      },
      {
        "page": "/blog/2026-02-26-echonest-sync-and-the-spotify-api-shakeup",
        "pageViews": 20
      }
    ]
  },
  "webVitals": {
    "lastCheck": "2026-03-13T06:16:37.143Z",
    "source": "rum",
    "metrics": {
      "TTFB": {
        "count": 149,
        "average": 241.16107382550337,
        "unit": "ms",
        "ratings": {
          "good": 145,
          "needs-improvement": 4,
          "poor": 0
        },
        "goodPercent": 97
      },
      "FCP": {
        "count": 85,
        "average": 838.1411764705882,
        "unit": "ms",
        "ratings": {
          "good": 74,
          "needs-improvement": 8,
          "poor": 3
        },
        "goodPercent": 87
      },
      "LCP": {
        "count": 26,
        "average": 1391.3846153846155,
        "unit": "ms",
        "ratings": {
          "good": 21,
          "needs-improvement": 2,
          "poor": 3
        },
        "goodPercent": 81
      },
      "CLS": {
        "count": 21,
        "average": 0.01480952380952381,
        "unit": "",
        "ratings": {
          "good": 20,
          "needs-improvement": 1,
          "poor": 0
        },
        "goodPercent": 95
      },
      "INP": {
        "count": 13,
        "average": 81.84615384615384,
        "unit": "ms",
        "ratings": {
          "good": 12,
          "needs-improvement": 1,
          "poor": 0
        },
        "goodPercent": 92
      }
    }
  }
}