{
  "generated": "2026-02-02T16:10:55.740Z",
  "searchConsole": {
    "lastCheck": "2026-01-12T11:03:07.421Z",
    "clicks": 0,
    "impressions": 1,
    "averageCTR": 0,
    "averagePosition": 1
  },
  "analytics": {
    "lastCheck": "2026-02-02T16:10:55.740Z",
    "sessions_7d": 1121,
    "users_7d": 1051,
    "pageviews_7d": 1088,
    "avgSessionDuration": 32,
    "bounceRate": 0.85,
    "topPages": [
      {
        "page": "/",
        "pageViews": 247
      },
      {
        "page": "/blog/",
        "pageViews": 140
      },
      {
        "page": "/runbook/",
        "pageViews": 80
      },
      {
        "page": "/blog",
        "pageViews": 75
      },
      {
        "page": "/runbook",
        "pageViews": 75
      }
    ]
  },
  "webVitals": {
    "lastCheck": "2026-02-02T16:10:55.740Z",
    "source": "rum",
    "metrics": {
      "TTFB": {
        "count": 433,
        "average": 340.83602771362587,
        "unit": "ms"
      },
      "FCP": {
        "count": 395,
        "average": 798.506329113924,
        "unit": "ms"
      },
      "LCP": {
        "count": 61,
        "average": 435.2950819672131,
        "unit": "ms"
      },
      "INP": {
        "count": 57,
        "average": 546.6666666666666,
        "unit": "ms"
      },
      "CLS": {
        "count": 18,
        "average": 0.012555555555555556,
        "unit": ""
      }
    }
  }
}