{
  "generated": "2026-07-18T07:37:59.720Z",
  "searchConsole": {
    "lastCheck": "2026-07-18T07:37:29.897Z",
    "clicks": 3,
    "impressions": 916,
    "averageCTR": 0.33,
    "averagePosition": 9
  },
  "analytics": {
    "lastCheck": "2026-07-18T07:37:59.178Z",
    "sessions_7d": 1022,
    "users_7d": 1009,
    "pageviews_7d": 1032,
    "avgSessionDuration": 19,
    "bounceRate": 0.93,
    "topPages": [
      {
        "page": "/blog",
        "pageViews": 185
      },
      {
        "page": "/",
        "pageViews": 176
      },
      {
        "page": "/runbook",
        "pageViews": 149
      },
      {
        "page": "/blog/2026-07-12-the-home-automation-system-that-is-not-allowed-to-automate",
        "pageViews": 96
      },
      {
        "page": "/projects",
        "pageViews": 69
      }
    ]
  },
  "webVitals": {
    "lastCheck": "2026-07-18T07:37:59.178Z",
    "source": "rum",
    "metrics": {
      "TTFB": {
        "count": 1517,
        "average": 67.87079762689518,
        "unit": "ms",
        "ratings": {
          "good": 1504,
          "needs-improvement": 7,
          "poor": 6
        },
        "goodPercent": 99
      },
      "FCP": {
        "count": 946,
        "average": 321.95348837209303,
        "unit": "ms",
        "ratings": {
          "good": 922,
          "needs-improvement": 19,
          "poor": 5
        },
        "goodPercent": 97
      },
      "LCP": {
        "count": 408,
        "average": 711.8382352941177,
        "unit": "ms",
        "ratings": {
          "good": 404,
          "needs-improvement": 4,
          "poor": 0
        },
        "goodPercent": 99
      },
      "CLS": {
        "count": 404,
        "average": 0.042707920792079204,
        "unit": "",
        "ratings": {
          "good": 311,
          "needs-improvement": 93,
          "poor": 0
        },
        "goodPercent": 77
      },
      "INP": {
        "count": 13,
        "average": 70.76923076923077,
        "unit": "ms",
        "ratings": {
          "good": 13,
          "needs-improvement": 0,
          "poor": 0
        },
        "goodPercent": 100
      }
    }
  }
}